pymx/__init__.py
pymx/ide/__init__.py
pymx/ide/editor.py
pymx/mcp/__init__.py
pymx/mcp/main.py
pymx/mcp/mendix_context.py
pymx/mcp/server.py
pymx/mcp/tool_registry.py
pymx/mcp/tools/__init__.py
pymx/mcp/tools/mendix_constant.py
pymx/mcp/tools/mendix_entity.py
pymx/mcp/tools/mendix_enum.py
pymx/mcp/tools/mendix_folder.py
pymx/mcp/tools/mendix_ide.py
pymx/mcp/tools/mendix_microflow.py
pymx/mcp/tools/mendix_module.py
pymx/mcp/tools/mendix_page.py
pymx/mcp/tools/mendix_settings.py
pymx/mcp/tools/mendix_untype.py
pymx/model/__init__.py
pymx/model/constant.py
pymx/model/entity.py
pymx/model/enum.py
pymx/model/folder.py
pymx/model/microflow.py
pymx/model/module.py
pymx/model/page.py
pymx/model/settings.py
pymx/model/untype.py
pymx/model/util.py
pymx/model/dto/__init__.py
pymx/model/dto/type_microflow.py
pymx/model/dto/type_settings.py
pymx-1.4.1.dist-info/licenses/LICENSE
pymx-1.4.1.dist-info/METADATA
pymx-1.4.1.dist-info/WHEEL
pymx-1.4.1.dist-info/top_level.txt
pymx-1.4.1.dist-info/RECORD
