Metadata-Version: 2.4
Name: pymx
Version: 1.4.1
Summary: A mendix extension library implement mcp server.
Author-email: wengao liu <engalar@gmail.com>
Project-URL: Homepage, https://github.com/engalar/MendixExtensionPython
Project-URL: Bug Tracker, https://github.com/engalar/MendixExtensionPython/issues
Classifier: Programming Language :: Python :: 3
Classifier: Operating System :: OS Independent
Requires-Python: >=3.11
License-File: LICENSE
Requires-Dist: starlette>=0.27.0
Requires-Dist: uvicorn>=0.23.2
Requires-Dist: requests>=2.31.0
Requires-Dist: pythonnet==3.0.5
Requires-Dist: anyio==4.9.0
Requires-Dist: pydantic>=2.11.1
Requires-Dist: typing-extensions==4.13.0
Requires-Dist: mcp==1.12.2
Requires-Dist: sse_starlette==1.6.5
Requires-Dist: setuptools==65.5.0
Dynamic: license-file
